README.md
setup.py
pulumi_kafkaconnect/__init__.py
pulumi_kafkaconnect/_utilities.py
pulumi_kafkaconnect/provider.py
pulumi_kafkaconnect/pulumi-plugin.json
pulumi_kafkaconnect/py.typed
pulumi_kafkaconnect.egg-info/PKG-INFO
pulumi_kafkaconnect.egg-info/SOURCES.txt
pulumi_kafkaconnect.egg-info/dependency_links.txt
pulumi_kafkaconnect.egg-info/not-zip-safe
pulumi_kafkaconnect.egg-info/requires.txt
pulumi_kafkaconnect.egg-info/top_level.txt
pulumi_kafkaconnect/config/__init__.py
pulumi_kafkaconnect/config/vars.py
pulumi_kafkaconnect/connector/__init__.py
pulumi_kafkaconnect/connector/connector.py