Metadata-Version: 2.1
Name: pulumi-kafkaconnect
Version: 0.0.10
Summary: A Pulumi native provider for Kafka Connect
Home-page: UNKNOWN
License: Apache-2.0
Project-URL: Repository, https://github.com/azaurus1/pulumi-kafka-connect
Keywords: pulumi kafka kafkaconnect category/utility kind/native
Platform: UNKNOWN
Requires-Python: >=3.9
